odoo9_addon_medical_pharmacy_us-9.0.1.0.0-py2.7-nspkg.pth
odoo_addons/medical_pharmacy_us/__openerp__.py
odoo_addons/medical_pharmacy_us/__init__.py
odoo_addons/medical_pharmacy_us/README.rst
odoo_addons/medical_pharmacy_us/models/__init__.py
odoo_addons/medical_pharmacy_us/models/medical_pharmacy.py
odoo_addons/medical_pharmacy_us/tests/test_medical_pharmacy.py
odoo_addons/medical_pharmacy_us/tests/__init__.py
odoo9_addon_medical_pharmacy_us-9.0.1.0.0.dist-info/top_level.txt
odoo9_addon_medical_pharmacy_us-9.0.1.0.0.dist-info/WHEEL
odoo9_addon_medical_pharmacy_us-9.0.1.0.0.dist-info/RECORD
odoo9_addon_medical_pharmacy_us-9.0.1.0.0.dist-info/metadata.json
odoo9_addon_medical_pharmacy_us-9.0.1.0.0.dist-info/DESCRIPTION.rst
odoo9_addon_medical_pharmacy_us-9.0.1.0.0.dist-info/METADATA
odoo9_addon_medical_pharmacy_us-9.0.1.0.0.dist-info/namespace_packages.txt
